pydantic_generator/__init__.py
pydantic_generator/cli.py
pydantic_generator/core/__init__.py
pydantic_generator/core/generator.py
pydantic_generator/core/parser/__init__.py
pydantic_generator/core/parser/base.py
pydantic_generator/core/parser/json_parser.py
pydantic_generator/main.py
pydantic_generator-1.0.0.dist-info/entry_points.txt
pydantic_generator-1.0.0.dist-info/LICENSE
pydantic_generator-1.0.0.dist-info/WHEEL
pydantic_generator-1.0.0.dist-info/METADATA
pydantic_generator-1.0.0.dist-info/RECORD
