Metadata-Version: 2.1
Name: pydantic-generator
Version: 1.0.0
Summary: pydantic-generator generates the pydantic model classes.
Home-page: https://github.com/rhoboro/pydantic-generator
License: MIT
Author: rhoboro
Author-email: rhoboro@gmail.com
Requires-Python: >=3.9,<4.0
Classifier: License :: OSI Approved :: MIT License
Classifier: Programming Language :: Python :: 3
Classifier: Programming Language :: Python :: 3.9
Project-URL: Repository, https://github.com/rhoboro/pydantic-generator
